{"title":"Token Meta Detection 1","evaluationState":"uninitialized","activityEntities":["experimentCreated",[{"id":"96B56F28-182C-4019-9809-35518687C231","title":"Model Source Created","subtitle":"Token Meta Detection 1","createdDate":"2025-06-25T20:37:04Z","event":"experimentCreated"}]],"id":"06AD0F39-9732-48EA-AC2F-3D730508A575","evaluationEntity":{"id":"775fcc6f-816f-4a64-b63f-352255125efb","dataResult":{},"analysedDataType":"none"},"createdDate":"2025-06-25T20:37:04Z","preferredFilename":"Token Meta Detection 1","evaluationContainerEntity":{"trainingEvaluationEntity":{"id":"4b5f79cc-991b-466d-a74e-cfc23f742b8b","analysedDataType":"none","createdDate":"2025-06-25T20:37:04Z","dataResult":{}},"testingEvaluationEntity":{"id":"df6abbb1-6ae5-4094-b1e5-ba1b3d10bbc6","analysedDataType":"none","createdDate":"2025-06-25T20:37:04Z","dataResult":{}},"evaluationEntities":[],"validationEvaluationEntity":{"id":"ec2dda17-d6aa-40f2-a66b-10201dccb35d","analysedDataType":"none","createdDate":"2025-06-25T20:37:04Z","dataResult":{}},"createdDate":"2025-06-25T20:37:04Z","id":"fb4c10fc-0801-4d28-987c-4939382344d4","previewType":"textClassifier","modifiedDate":"2025-06-25T20:37:04Z"},"version":"1.0","modifiedDate":"2025-06-25T20:37:04Z","contentDataResult":{},"snapshotRole":{"withoutSnapshots":0},"state":"uninitialized","trainingEntity":{"snapshottableCheckpoints":{},"checkpointMetrics":{},"dataResult":{},"analysedDataType":"choose","featureExtractionCheckpointMayBeAvailable":false,"progress":[]},"settingEntity":{"taskType":"textClassifier","handActionClassifierAugmentations":[],"styleTransferAlgorithmType":"image","augmentations":[],"handPoseClassifierAugmentations":[],"seedType":"default","algorithmType":"maxEnt","harVideoAugmentations":0,"featureNames":[]},"modelEntity":{"preferredFilename":"","id":"B0973085-5331-4D3F-BF23-9E4BE94C6A0F","modifiedDate":"2025-06-25T20:37:04Z","createdDate":"2025-06-25T20:37:04Z","title":"","experimentID":"06AD0F39-9732-48EA-AC2F-3D730508A575","version":"1.0"},"validationEntity":{"analysedDataType":"auto","dataResult":{}}}